streamlit_3d/__init__.py
streamlit_3d/frontend/index.html
streamlit_3d/frontend/main.js
streamlit_3d/frontend/streamlit-component-lib.js
streamlit_3d/frontend/style.css
streamlit_3d-0.1.12.dist-info/LICENSE
streamlit_3d-0.1.12.dist-info/METADATA
streamlit_3d-0.1.12.dist-info/WHEEL
streamlit_3d-0.1.12.dist-info/top_level.txt
streamlit_3d-0.1.12.dist-info/RECORD
