Metadata-Version: 2.1
Name: streamlit-3d
Version: 0.1.12
Summary: 3d model viewer
Author: Anthony Alteirac
Author-email: anthony@alteirac.com
Requires-Python: >=3.7
License-File: LICENSE
